tests/__init__.py
tests/test_api.py
versacorellmchatapi/__init__.py
versacorellmchatapi/api.py
versacorellmchatapi-0.1.9.dist-info/LICENSE
versacorellmchatapi-0.1.9.dist-info/METADATA
versacorellmchatapi-0.1.9.dist-info/WHEEL
versacorellmchatapi-0.1.9.dist-info/top_level.txt
versacorellmchatapi-0.1.9.dist-info/RECORD
