Metadata-Version: 2.1
Name: versacorellmchatapi
Version: 0.1.9
Summary: A Python library for interacting with the VersaCore LLM Chat API.
Home-page: https://github.com/AI-Sherpa/versacorellmchatapi
Author: Jansen Tang
Author-email: jansen.tang@ai-sherpa.io
Classifier: Programming Language :: Python :: 3
Classifier: License :: OSI Approved :: MIT License
Classifier: Operating System :: OS Independent
Requires-Python: >=3.6
License-File: LICENSE
Requires-Dist: requests
